bangsue_codename/BangsueCodename.py
bangsue_codename/__init__.py
bangsue_codename/file/bts_skytrain.csv
bangsue_codename/file/mrta_train.csv
bangsue_codename/file/red_skytrain.csv
bangsue_codename/file/tambon_bse.csv
bangsue-2.0.3.dist-info/METADATA
bangsue-2.0.3.dist-info/WHEEL
bangsue-2.0.3.dist-info/top_level.txt
bangsue-2.0.3.dist-info/RECORD
