Metadata-Version: 2.1
Name: bangsue
Version: 2.0.3
Summary: Bangsue. Thai Codename Generator
Home-page: https://github.com/aphisitworachorch/bangsue
Author: ARSANANDHA
Author-email: arsanandha.ap@gmail.com
Classifier: Programming Language :: Python :: 3
Classifier: License :: OSI Approved :: MIT License
Classifier: Operating System :: OS Independent
Requires-Python: >=3.6
Requires-Dist: numpy
